setup.py
kjlib/__init__.py
kjlib/application.py
kjlib/debugtools.py
kjlib/iniparser.py
kjlib/jobcontrol.py
kjlib/meta.py
kjlib/mycollections.py
kjlib/printers.py
kjlib/timetools.py
kjlib/tools.py
kjlib.egg-info/PKG-INFO
kjlib.egg-info/SOURCES.txt
kjlib.egg-info/dependency_links.txt
kjlib.egg-info/requires.txt
kjlib.egg-info/top_level.txt