Metadata-Version: 1.0
Name: kjlib
Version: 2.1.0
Summary: Reusable Python Modules
Home-page: https://github.com/legion0/kjlib-python
Author: K Jonathan
Author-email: phenixdoc@gmail.com
License: UNKNOWN
Platform: UNKNOWN
